README.md
setup.py
donnie/__init__.py
donnie/brain.py
donnie/poloapi.py
donnie/tools.py
donnie.egg-info/PKG-INFO
donnie.egg-info/SOURCES.txt
donnie.egg-info/dependency_links.txt
donnie.egg-info/not-zip-safe
donnie.egg-info/requires.txt
donnie.egg-info/top_level.txt