Metadata-Version: 2.1
Name: donnie
Version: 0.0.4
Summary: Poloniex tradebot toolkit
Home-page: https://github.com/s4w3d0ff/donnie
Author: s4w3d0ff
License: GPL v3
Keywords: poloniex,poloniexapi,exchange,api,tradebot,framework
Platform: UNKNOWN
Classifier: Operating System :: MacOS :: MacOS X
Classifier: Operating System :: Microsoft :: Windows
Classifier: Operating System :: POSIX
Classifier: License :: OSI Approved :: GNU General Public License v3 (GPLv3)
Classifier: Programming Language :: Python :: 3
